qcnpy/__init__.py
qcnpy/__version__.py
qcnpy/analysis.py
qcnpy/ansatzes.py
qcnpy/costfunction.py
qcnpy/data_encoders.py
qcnpy/layers.py
qcnpy/neuralnetwork.py
qcnpy/optimizers.py
qcnpy/parametrizations.py
qcnpy/rco.py
qcnpy/samplers.py
qcnpy/utils.py
qcnpy-0.0.1.dist-info/LICENSE
qcnpy-0.0.1.dist-info/METADATA
qcnpy-0.0.1.dist-info/WHEEL
qcnpy-0.0.1.dist-info/top_level.txt
qcnpy-0.0.1.dist-info/RECORD
